geheim/__init__.py
geheim/super_geheim.py
geheim-0.0.3.dist-info/LICENSE
geheim-0.0.3.dist-info/METADATA
geheim-0.0.3.dist-info/WHEEL
geheim-0.0.3.dist-info/top_level.txt
geheim-0.0.3.dist-info/RECORD
