Metadata-Version: 2.1
Name: geheim
Version: 0.0.3
Summary: A small example package
Home-page: https://github.com/pypa/sampleproject
Author: Jan Sternagel
Author-email: jan.sternagel@gmail.com
License: UNKNOWN
Project-URL: Bug Tracker, https://github.com/pypa/sampleproject/issues
Platform: UNKNOWN
Classifier: Programming Language :: Python :: 3
Classifier: License :: OSI Approved :: MIT License
Classifier: Operating System :: OS Independent
Requires-Python: >=3.6
License-File: LICENSE
